specific_import/__init__.py
specific_import/specific_import.py
specific_import-0.9.6.dist-info/METADATA
specific_import-0.9.6.dist-info/WHEEL
specific_import-0.9.6.dist-info/top_level.txt
specific_import-0.9.6.dist-info/RECORD
