Metadata-Version: 2.1
Name: specific_import
Version: 0.9.6
Summary: This package simplifies importing relative and absolute module paths
Home-page: https://github.com/sudouser2010/specific_import
Author: Hadron DaVinci
Project-URL: Bug Tracker, https://github.com/sudouser2010/specific_import/issues
Classifier: Programming Language :: Python :: 3
Classifier: License :: OSI Approved :: MIT License
Classifier: Operating System :: OS Independent
Requires-Python: >=3.6
